ai_assistant/test.py
ai_assistant_by_timurkarev-0.1.0.dist-info/METADATA
ai_assistant_by_timurkarev-0.1.0.dist-info/WHEEL
ai_assistant_by_timurkarev-0.1.0.dist-info/top_level.txt
ai_assistant_by_timurkarev-0.1.0.dist-info/RECORD
