Metadata-Version: 2.1
Name: ai-assistant-by-timurkarev
Version: 0.1.0
Summary: AI Assistant
Author: Timur Karev
